xyzzy_fork/__init__.py
xyzzy_fork/py.typed
xyzzy_fork-1.0.1.dist-info/METADATA
xyzzy_fork-1.0.1.dist-info/WHEEL
xyzzy_fork-1.0.1.dist-info/licenses/LICENSE
xyzzy_fork-1.0.1.dist-info/RECORD
