Metadata-Version: 2.3
Name: xyzzy-fork
Version: 1.0.1
Summary: A package to use for the gnomic message "xyzzy"
Author-email: Darshan Shaligram <scintilla@gmail.com>
License-File: LICENSE
Classifier: License :: OSI Approved :: MIT License
Classifier: Operating System :: OS Independent
Classifier: Typing :: Typed
Requires-Python: >=3.8
